flask_pg_session/__init__.py
flask_pg_session/_queries.py
flask_pg_session/_utils.py
flask_pg_session/session.py
flask_pg_session-0.1.0.dist-info/LICENSE
flask_pg_session-0.1.0.dist-info/METADATA
flask_pg_session-0.1.0.dist-info/WHEEL
flask_pg_session-0.1.0.dist-info/RECORD
