Metadata-Version: 2.1
Name: flask-pg-session
Version: 0.1.0
Summary: Flask extension that implements server-side sessions in PostgreSQL
Home-page: https://github.com/giuppep/flask-pg-session
License: MIT
Keywords: flask,server-side session,session
Author: Giuseppe Papallo
Author-email: giuseppe@papallo.it
Requires-Python: >3.8.1
Classifier: License :: OSI Approved :: MIT License
Classifier: Programming Language :: Python :: 3
Classifier: Programming Language :: Python :: 3.9
Classifier: Programming Language :: Python :: 3.10
Classifier: Programming Language :: Python :: 3.11
Requires-Dist: flask (>1)
Requires-Dist: psycopg2-binary (>2)
Project-URL: Bug Tracker, https://github.com/giuppep/flask-pg-session/issues
Project-URL: Documentation, https://github.com/giuppep/flask-pg-session#readme
Project-URL: Repository, https://github.com/giuppep/flask-pg-session
